twitscrape/__init__.py
twitscrape/twitter_scraper.py
twitscrape-0.0.7.dist-info/LICENSE
twitscrape-0.0.7.dist-info/METADATA
twitscrape-0.0.7.dist-info/WHEEL
twitscrape-0.0.7.dist-info/top_level.txt
twitscrape-0.0.7.dist-info/RECORD
