Metadata-Version: 2.1
Name: twitscrape
Version: 0.0.7
Summary: Simple package using Selenium to scrape tweet data based on geolocation and datetime
Author-email: Christian Harrison <christywastakenwastaken@gmail.com>
Project-URL: Homepage, https://github.com/christywastaken/twitscrape
Project-URL: Bug Tracker, https://github.com/christywastaken/twitscrape/issues
Classifier: Programming Language :: Python :: 3
Classifier: License :: OSI Approved :: MIT License
Classifier: Operating System :: OS Independent
Requires-Python: >=3.7
License-File: LICENSE
Requires-Dist: selenium-wire (>=5.1.0)
Requires-Dist: pandas (>=1.5.3)
Requires-Dist: webdriver-manager (>=3.8.5)
